mapeathor/__init__.py
mapeathor/__main__.py
mapeathor/_version.py
mapeathor/api.py
mapeathor/global_config.py
mapeathor/mapping_generator.py
mapeathor/mapping_writer.py
mapeathor/source.py
mapeathor/utils.py
mapeathor/templates/r2rml/Base.tmpl
mapeathor/templates/r2rml/Function.tmpl
mapeathor/templates/r2rml/Join.tmpl
mapeathor/templates/r2rml/POM.tmpl
mapeathor/templates/r2rml/Prefix.tmpl
mapeathor/templates/r2rml/Source.tmpl
mapeathor/templates/r2rml/SourceQuery.tmpl
mapeathor/templates/r2rml/Subject.tmpl
mapeathor/templates/r2rml/TriplesMap.tmpl
mapeathor/templates/r2rml/config.json
mapeathor/templates/r2rml/structure.json
mapeathor/templates/rml/Base.tmpl
mapeathor/templates/rml/Function.tmpl
mapeathor/templates/rml/FunctionMap.tmpl
mapeathor/templates/rml/FunctionPOM.tmpl
mapeathor/templates/rml/FunctionSource.tmpl
mapeathor/templates/rml/Join.tmpl
mapeathor/templates/rml/POM.tmpl
mapeathor/templates/rml/Prefix.tmpl
mapeathor/templates/rml/Source.tmpl
mapeathor/templates/rml/SourceQuery.tmpl
mapeathor/templates/rml/Subject.tmpl
mapeathor/templates/rml/TriplesMap.tmpl
mapeathor/templates/rml/config.json
mapeathor/templates/rml/rmlMapping.json
mapeathor/templates/rml/structure.json
mapeathor/templates/rml2014/Base.tmpl
mapeathor/templates/rml2014/Function.tmpl
mapeathor/templates/rml2014/FunctionMap.tmpl
mapeathor/templates/rml2014/FunctionPOM.tmpl
mapeathor/templates/rml2014/FunctionSource.tmpl
mapeathor/templates/rml2014/Join.tmpl
mapeathor/templates/rml2014/POM.tmpl
mapeathor/templates/rml2014/Prefix.tmpl
mapeathor/templates/rml2014/Source.tmpl
mapeathor/templates/rml2014/SourceQuery.tmpl
mapeathor/templates/rml2014/Subject.tmpl
mapeathor/templates/rml2014/TriplesMap.tmpl
mapeathor/templates/rml2014/config.json
mapeathor/templates/rml2014/rmlMapping.json
mapeathor/templates/rml2014/structure.json
mapeathor/templates/yarrrml/Base.tmpl
mapeathor/templates/yarrrml/Function.tmpl
mapeathor/templates/yarrrml/Join.tmpl
mapeathor/templates/yarrrml/POM.tmpl
mapeathor-1.7.5.dist-info/METADATA
mapeathor-1.7.5.dist-info/WHEEL
mapeathor-1.7.5.dist-info/top_level.txt
mapeathor-1.7.5.dist-info/RECORD
