Metadata-Version: 2.1
Name: mapeathor
Version: 1.7.5
Summary: Mapeathor translates your mapping rules specified in spreadsheets to a mapping language.
Home-page: https://github.com/oeg-upm/Mapeathor
Author: Ana Iglesias-Molina
Author-email: Ana Iglesias-Molina <ana.iglesiasm@upm.es>
License: Apache License
Project-URL: Documentation, https://github.com/oeg-upm/mapeathor/wiki
Project-URL: Source, https://github.com/oeg-upm/mapeathor/
Project-URL: Tracker, https://github.com/oeg-upm/mapeathor/issues
Project-URL: CI, https://github.com/oeg-upm/mapeathor/actions
Project-URL: Homepage, https://morph.oeg.fi.upm.es/tool/mapeathor
Project-URL: History, https://github.com/oeg-upm/mapeathor/actions
Keywords: Mapeathor,R2RML,RML,YARRRML,Knowledge Graph,Data Integration
Classifier: Programming Language :: Python :: 3
Classifier: Programming Language :: Python :: 3.6
Classifier: Programming Language :: Python :: 3.7
Classifier: Programming Language :: Python :: 3.8
Classifier: Programming Language :: Python :: 3.9
Classifier: Programming Language :: Python :: 3.10
Classifier: Programming Language :: Python :: 3.11
Classifier: License :: OSI Approved :: Apache Software License
Classifier: Operating System :: OS Independent
Classifier: Development Status :: 5 - Production/Stable
Classifier: Environment :: Console
Classifier: Intended Audience :: Information Technology
Classifier: Intended Audience :: Science/Research
Classifier: Topic :: Software Development :: Pre-processors
Classifier: Topic :: Utilities
Classifier: Topic :: Scientific/Engineering :: Interface Engine/Protocol Translator
Requires-Python: >=3.6
Requires-Dist: pandas
Requires-Dist: argparse
Requires-Dist: openpyxl
Requires-Dist: httplib2
Requires-Dist: configparser
Requires-Dist: flask
Requires-Dist: flask-swagger
Requires-Dist: flask-swagger-ui
Requires-Dist: flask-restful
Requires-Dist: requests
Requires-Dist: jinja2
